README
setup.py
CFAnalyze.egg-info/PKG-INFO
CFAnalyze.egg-info/SOURCES.txt
CFAnalyze.egg-info/dependency_links.txt
CFAnalyze.egg-info/entry_points.txt
CFAnalyze.egg-info/requires.txt
CFAnalyze.egg-info/top_level.txt
cfanalyze/__init__.py
cfanalyze/__main__.py
cfanalyze/analyze.py
cfanalyze/fetch.py