Metadata-Version: 1.0
Name: CFAnalyze
Version: 0.0.1
Summary: Just Simple Amazon CloudFront Access Log Analyzer
Home-page: https://github.com/kkung/cfanalyze
Author: MinYoung Jung
Author-email: kkungkkung@gmail.com
License: MIT License
Keywords: aws cloudfront cf analyze
Platform: UNKNOWN
Classifier: Development Status :: 4 - Beta
Classifier: License :: OSI Approved :: MIT License
Classifier: Operating System :: OS Independent
